LICENSE
MANIFEST.in
README.md
setup.cfg
setup.py
pretix_ldap_mails/__init__.py
pretix_ldap_mails/signals.py
pretix_ldap_mails.egg-info/PKG-INFO
pretix_ldap_mails.egg-info/SOURCES.txt
pretix_ldap_mails.egg-info/dependency_links.txt
pretix_ldap_mails.egg-info/entry_points.txt
pretix_ldap_mails.egg-info/top_level.txt
pretix_ldap_mails/locale/django.pot
pretix_ldap_mails/locale/de/LC_MESSAGES/django.mo
pretix_ldap_mails/locale/de/LC_MESSAGES/django.po
pretix_ldap_mails/locale/de_Informal/.gitkeep
pretix_ldap_mails/locale/de_Informal/LC_MESSAGES/django.mo
pretix_ldap_mails/locale/de_Informal/LC_MESSAGES/django.po
pretix_ldap_mails/static/pretix_verify_mails/.gitkeep
pretix_ldap_mails/templates/pretix_verify_mails/.gitkeep