Metadata-Version: 2.1
Name: pretix-ldap-mails
Version: 1.0.0
Summary: Verify user supplied mails against LDAP
Home-page: https://github.com/kagonlineteam/pretix-ldap-mails
Author: strifel
Author-email: info@strifel.de
License: Apache
License-File: LICENSE
